README.md
setup.py
srplasticity/__init__.py
srplasticity/inference.py
srplasticity/models.py
srplasticity/srp.py
srplasticity/tm.py
srplasticity/tools.py
srplasticity.egg-info/PKG-INFO
srplasticity.egg-info/SOURCES.txt
srplasticity.egg-info/dependency_links.txt
srplasticity.egg-info/not-zip-safe
srplasticity.egg-info/requires.txt
srplasticity.egg-info/top_level.txt