Metadata-Version: 2.1
Name: srplasticity
Version: 0.0.1
Summary: UNKNOWN
Home-page: https://github.com/nauralcodinglab/srplasticity.git
Author: Julian Rossbroich, Daniel Trotter, John Beninger, Richard Naud
Author-email: jbeni014@uottawa.ca
License: GPLv3
Platform: UNKNOWN
Classifier: Development Status :: 2 - Pre-Alpha
Classifier: Programming Language :: Python :: 3.8
